{
  "openapi": "3.0.1",
  "info": {
    "title": "MessageBoard.Solution",
    "version": "1.0"
  },
  "paths": {
    "/api/Groups": {
      "get": {
        "tags": [
          "Groups"
        ],
        "parameters": [
          {
            "name": "groupId",
            "in": "query",
            "schema": {
              "type": "integer",
              "format": "int32",
              "nullable": true
            }
          }
        ],
        "responses": {
          "200": {
            "description": "Success",
            "content": {
              "text/plain": {
                "schema": {
                  "type": "array",
                  "items": {
                    "$ref": "#/components/schemas/Group"
                  }
                }
              },
              "application/json": {
                "schema": {
                  "type": "array",
                  "items": {
                    "$ref": "#/components/schemas/Group"
                  }
                }
              },
              "text/json": {
                "schema": {
                  "type": "array",
                  "items": {
                    "$ref": "#/components/schemas/Group"
                  }
                }
              }
            }
          }
        }
      },
      "post": {
        "tags": [
          "Groups"
        ],
        "requestBody": {
          "content": {
            "application/json-patch+json": {
              "schema": {
                "$ref": "#/components/schemas/Group"
              }
            },
            "application/json": {
              "schema": {
                "$ref": "#/components/schemas/Group"
              }
            },
            "text/json": {
              "schema": {
                "$ref": "#/components/schemas/Group"
              }
            },
            "application/*+json": {
              "schema": {
                "$ref": "#/components/schemas/Group"
              }
            }
          }
        },
        "responses": {
          "200": {
            "description": "Success"
          }
        }
      }
    },
    "/api/Messages": {
      "get": {
        "tags": [
          "Messages"
        ],
        "parameters": [
          {
            "name": "user",
            "in": "query",
            "schema": {
              "type": "string",
              "nullable": true
            }
          },
          {
            "name": "startDate",
            "in": "query",
            "schema": {
              "type": "string",
              "format": "date-time",
              "nullable": true
            }
          },
          {
            "name": "endDate",
            "in": "query",
            "schema": {
              "type": "string",
              "format": "date-time",
              "nullable": true
            }
          }
        ],
        "responses": {
          "200": {
            "description": "Success",
            "content": {
              "text/plain": {
                "schema": {
                  "type": "array",
                  "items": {
                    "$ref": "#/components/schemas/Message"
                  }
                }
              },
              "application/json": {
                "schema": {
                  "type": "array",
                  "items": {
                    "$ref": "#/components/schemas/Message"
                  }
                }
              },
              "text/json": {
                "schema": {
                  "type": "array",
                  "items": {
                    "$ref": "#/components/schemas/Message"
                  }
                }
              }
            }
          }
        }
      },
      "post": {
        "tags": [
          "Messages"
        ],
        "requestBody": {
          "content": {
            "application/json-patch+json": {
              "schema": {
                "$ref": "#/components/schemas/Message"
              }
            },
            "application/json": {
              "schema": {
                "$ref": "#/components/schemas/Message"
              }
            },
            "text/json": {
              "schema": {
                "$ref": "#/components/schemas/Message"
              }
            },
            "application/*+json": {
              "schema": {
                "$ref": "#/components/schemas/Message"
              }
            }
          }
        },
        "responses": {
          "200": {
            "description": "Success"
          }
        }
      }
    },
    "/api/Messages/{id}": {
      "put": {
        "tags": [
          "Messages"
        ],
        "parameters": [
          {
            "name": "id",
            "in": "path",
            "required": true,
            "schema": {
              "type": "integer",
              "format": "int32"
            }
          }
        ],
        "requestBody": {
          "content": {
            "application/json-patch+json": {
              "schema": {
                "$ref": "#/components/schemas/Message"
              }
            },
            "application/json": {
              "schema": {
                "$ref": "#/components/schemas/Message"
              }
            },
            "text/json": {
              "schema": {
                "$ref": "#/components/schemas/Message"
              }
            },
            "application/*+json": {
              "schema": {
                "$ref": "#/components/schemas/Message"
              }
            }
          }
        },
        "responses": {
          "200": {
            "description": "Success"
          }
        }
      },
      "delete": {
        "tags": [
          "Messages"
        ],
        "parameters": [
          {
            "name": "id",
            "in": "path",
            "required": true,
            "schema": {
              "type": "integer",
              "format": "int32"
            }
          }
        ],
        "responses": {
          "200": {
            "description": "Success"
          }
        }
      }
    },
    "/Users/authenticate": {
      "post": {
        "tags": [
          "Users"
        ],
        "requestBody": {
          "content": {
            "application/json-patch+json": {
              "schema": {
                "$ref": "#/components/schemas/User"
              }
            },
            "application/json": {
              "schema": {
                "$ref": "#/components/schemas/User"
              }
            },
            "text/json": {
              "schema": {
                "$ref": "#/components/schemas/User"
              }
            },
            "application/*+json": {
              "schema": {
                "$ref": "#/components/schemas/User"
              }
            }
          }
        },
        "responses": {
          "200": {
            "description": "Success"
          }
        }
      }
    },
    "/Users": {
      "get": {
        "tags": [
          "Users"
        ],
        "responses": {
          "200": {
            "description": "Success"
          }
        }
      }
    },
    "/api/Values": {
      "get": {
        "tags": [
          "Values"
        ],
        "responses": {
          "200": {
            "description": "Success",
            "content": {
              "text/plain": {
                "schema": {
                  "type": "array",
                  "items": {
                    "type": "string"
                  }
                }
              },
              "application/json": {
                "schema": {
                  "type": "array",
                  "items": {
                    "type": "string"
                  }
                }
              },
              "text/json": {
                "schema": {
                  "type": "array",
                  "items": {
                    "type": "string"
                  }
                }
              }
            }
          }
        }
      },
      "post": {
        "tags": [
          "Values"
        ],
        "requestBody": {
          "content": {
            "application/json-patch+json": {
              "schema": {
                "type": "string",
                "nullable": true
              }
            },
            "application/json": {
              "schema": {
                "type": "string",
                "nullable": true
              }
            },
            "text/json": {
              "schema": {
                "type": "string",
                "nullable": true
              }
            },
            "application/*+json": {
              "schema": {
                "type": "string",
                "nullable": true
              }
            }
          }
        },
        "responses": {
          "200": {
            "description": "Success"
          }
        }
      }
    },
    "/api/Values/{id}": {
      "get": {
        "tags": [
          "Values"
        ],
        "parameters": [
          {
            "name": "id",
            "in": "path",
            "required": true,
            "schema": {
              "type": "integer",
              "format": "int32"
            }
          }
        ],
        "responses": {
          "200": {
            "description": "Success",
            "content": {
              "text/plain": {
                "schema": {
                  "type": "string"
                }
              },
              "application/json": {
                "schema": {
                  "type": "string"
                }
              },
              "text/json": {
                "schema": {
                  "type": "string"
                }
              }
            }
          }
        }
      },
      "put": {
        "tags": [
          "Values"
        ],
        "parameters": [
          {
            "name": "id",
            "in": "path",
            "required": true,
            "schema": {
              "type": "integer",
              "format": "int32"
            }
          }
        ],
        "requestBody": {
          "content": {
            "application/json-patch+json": {
              "schema": {
                "type": "string",
                "nullable": true
              }
            },
            "application/json": {
              "schema": {
                "type": "string",
                "nullable": true
              }
            },
            "text/json": {
              "schema": {
                "type": "string",
                "nullable": true
              }
            },
            "application/*+json": {
              "schema": {
                "type": "string",
                "nullable": true
              }
            }
          }
        },
        "responses": {
          "200": {
            "description": "Success"
          }
        }
      },
      "delete": {
        "tags": [
          "Values"
        ],
        "parameters": [
          {
            "name": "id",
            "in": "path",
            "required": true,
            "schema": {
              "type": "integer",
              "format": "int32"
            }
          }
        ],
        "responses": {
          "200": {
            "description": "Success"
          }
        }
      }
    }
  },
  "components": {
    "schemas": {
      "Message": {
        "type": "object",
        "properties": {
          "MessageId": {
            "type": "integer",
            "format": "int32"
          },
          "Title": {
            "type": "string",
            "nullable": true
          },
          "Body": {
            "type": "string",
            "nullable": true
          },
          "Date": {
            "type": "string",
            "format": "date-time"
          },
          "UserName": {
            "type": "string",
            "nullable": true
          },
          "GroupId": {
            "type": "integer",
            "format": "int32"
          }
        },
        "additionalProperties": false
      },
      "Group": {
        "type": "object",
        "properties": {
          "GroupId": {
            "type": "integer",
            "format": "int32"
          },
          "Name": {
            "type": "string",
            "nullable": true
          },
          "Messages": {
            "type": "array",
            "items": {
              "$ref": "#/components/schemas/Message"
            },
            "nullable": true
          }
        },
        "additionalProperties": false
      },
      "User": {
        "type": "object",
        "properties": {
          "Id": {
            "type": "integer",
            "format": "int32"
          },
          "FirstName": {
            "type": "string",
            "nullable": true
          },
          "LastName": {
            "type": "string",
            "nullable": true
          },
          "UserName": {
            "type": "string",
            "nullable": true
          },
          "Password": {
            "type": "string",
            "nullable": true
          },
          "Token": {
            "type": "string",
            "nullable": true
          }
        },
        "additionalProperties": false
      }
    }
  }
}